opencld/__init__.py
opencld/auxiliary.py
opencld/flow.py
opencld/model.py
opencld/multi_simulation.py
opencld/my_units.txt
opencld/parameter.py
opencld/plotting.py
opencld/stock.py
opencld/table.py
opencld/unit_manager.py
opencld/units.py
opencld-0.3.3.dist-info/licenses/LICENSE
opencld-0.3.3.dist-info/METADATA
opencld-0.3.3.dist-info/WHEEL
opencld-0.3.3.dist-info/RECORD
