Metadata-Version: 2.4
Name: opencld
Version: 0.3.3
Summary: OpenCLD - A hybrid System Dynamics and AI simulation library for building, running, and analyzing dynamic system models with unit-aware computations.
License: CC-BY-NC-ND-4.0
License-File: LICENSE
Keywords: system-dynamics,simulation,modeling,causal-loop,stock-flow,AI,hybrid-modeling
Author: Pietro Viero
Author-email: pietro.viero1@gmail.com
Requires-Python: >=3.9,<4.0
Classifier: Development Status :: 4 - Beta
Classifier: Intended Audience :: Science/Research
Classifier: Intended Audience :: Education
Classifier: License :: Other/Proprietary License
Classifier: Operating System :: OS Independent
Classifier: Programming Language :: Python :: 3
Classifier: Programming Language :: Python :: 3.9
Classifier: Programming Language :: Python :: 3.10
Classifier: Programming Language :: Python :: 3.11
Classifier: Programming Language :: Python :: 3.12
Classifier: Programming Language :: Python :: 3.13
Classifier: Topic :: Scientific/Engineering
Classifier: Topic :: Scientific/Engineering :: Artificial Intelligence
Requires-Dist: matplotlib (>=3.7.0)
Requires-Dist: networkx (>=3.0)
Requires-Dist: numpy (>=1.24.0)
Requires-Dist: pandas (>=2.0.0)
Requires-Dist: pint (>=0.22)
Requires-Dist: pydot (>=2.0.0)
Requires-Dist: seaborn (>=0.12.0)
Requires-Dist: tqdm (>=4.65.0)
Project-URL: Documentation, https://github.com/log-lab-polito/OpenCLD#readme
Project-URL: Homepage, https://github.com/log-lab-polito/OpenCLD
Project-URL: Issues, https://github.com/log-lab-polito/OpenCLD/issues
Project-URL: Repository, https://github.com/log-lab-polito/OpenCLD
